evrmorerpc/__init__.py
evrmorerpc/__main__.py
evrmorerpc/client.py
evrmorerpc/config.py
evrmorerpc/errors.py
evrmorerpc/methods.py
evrmorerpc/models/__init__.py
evrmorerpc/models/addressindex/__init__.py
evrmorerpc/models/assets/__init__.py
evrmorerpc/models/base/__init__.py
evrmorerpc/models/blockchain/__init__.py
evrmorerpc/models/control/__init__.py
evrmorerpc/models/generating/__init__.py
evrmorerpc/models/messages/__init__.py
evrmorerpc/models/mining/__init__.py
evrmorerpc/models/network/__init__.py
evrmorerpc/models/rawtx/__init__.py
evrmorerpc/models/restricted/__init__.py
evrmorerpc/models/rewards/__init__.py
evrmorerpc/models/util/__init__.py
evrmorerpc/models/wallet/__init__.py
evrmorerpc/zmq/README.md
evrmorerpc/zmq/__init__.py
evrmorerpc-1.0.1.dist-info/METADATA
evrmorerpc-1.0.1.dist-info/WHEEL
evrmorerpc-1.0.1.dist-info/licenses/LICENSE
evrmorerpc-1.0.1.dist-info/RECORD
