Metadata-Version: 2.4
Name: evrmorerpc
Version: 1.0.1
Summary: Python RPC client for Evrmore blockchain
Project-URL: Homepage, https://github.com/manticore-trade/evrmorerpc
Project-URL: Documentation, https://github.com/manticore-trade/evrmorerpc#readme
Project-URL: Repository, https://github.com/manticore-trade/evrmorerpc.git
Project-URL: Issues, https://github.com/manticore-trade/evrmorerpc/issues
Author-email: Manticore Technologies <accounting@manticore.email>
License: MIT License
License-File: LICENSE
Keywords: blockchain,cryptocurrency,evrmore,rpc
Classifier: Development Status :: 4 - Beta
Classifier: Intended Audience :: Developers
Classifier: License :: OSI Approved :: MIT License
Classifier: Programming Language :: Python :: 3
Classifier: Programming Language :: Python :: 3.8
Classifier: Programming Language :: Python :: 3.9
Classifier: Programming Language :: Python :: 3.10
Classifier: Programming Language :: Python :: 3.11
Classifier: Topic :: Internet
Classifier: Topic :: Software Development :: Libraries :: Python Modules
Classifier: Topic :: System :: Networking
Requires-Python: >=3.8
Requires-Dist: pydantic>=2.0.0
Requires-Dist: pyzmq>=25.0.0
Requires-Dist: requests>=2.25.0
